{
    "version":      1,
    "fileType":  "FactMetaData",
    "QGC.MetaData.Facts":
[
{
    "name":             "nav_longitude",
    "shortDesc":        "NAV_LONGITUDE",
    "type":             "double",
    "decimalPlaces":    7
},
{
    "name":             "nav_latitude",
    "shortDesc":        "NAV_LATITUDE",
    "type":             "double",
    "decimalPlaces":    7
},
{
    "name":             "nav_roll",
    "shortDesc":        "NAV_ROLL",
    "type":             "float",
    "decimalPlaces":        2,
    "default":              null
},
{
    "name":             "nav_pitch",
    "shortDesc":        "NAV_PITCH",
    "type":             "float",
    "decimalPlaces":        2,
    "default":              null
},
{
    "name":             "nav_yaw",
    "shortDesc":        "NAV_YAW",
    "type":             "float",
    "decimalPlaces":        2,
    "default":              null
},
{
    "name":             "nav_yaw_rate",
    "shortDesc":        "NAV_YAW_RATE",
    "type":             "float",
    "decimalPlaces":        2,
    "default":              null
},
{
    "name":             "nav_cog",
    "shortDesc":        "NAV_COG",
    "type":             "float",
    "decimalPlaces":        2,
    "default":              null
},
{
    "name":             "nav_sog",
    "shortDesc":        "NAV_SOG",
    "type":             "float",
    "decimalPlaces":        2,
    "default":              null
},
{
    "name":             "nav_uspd",
    "shortDesc":        "NAV_USPD",
    "type":             "float",
    "decimalPlaces":        2,
    "default":              null
},
{
    "name":             "nav_vspd",
    "shortDesc":        "NAV_VSPD",
    "type":             "float",
    "decimalPlaces":        2,
    "default":              null
},
{
    "name":             "nav_wspd",
    "shortDesc":        "NAV_WSPD",
    "type":             "float",
    "decimalPlaces":        2,
    "default":              null
},
{
    "name":             "nav_heave",
    "shortDesc":        "NAV_HEAVE",
    "type":             "float",
    "decimalPlaces":        2,
    "default":              null
},
{
    "name":             "nav_gpstime",
    "shortDesc":        "NAV_GPSTIME",
    "type":             "float",
    "decimalPlaces":        2,
    "default":              null
},
{
    "name":             "wea_airtem",
    "shortDesc":        "WEA_AIRTEM",
    "type":             "float",
    "decimalPlaces":        2,
    "default":              null
},
{
    "name":             "wea_wattem",
    "shortDesc":        "WEA_WATTEM",
    "type":             "float",
    "decimalPlaces":        2,
    "default":              null
},
{
    "name":             "wea_press",
    "shortDesc":        "WEA_PRESS",
    "type":             "float",
    "decimalPlaces":        2,
    "default":              null
},
{
    "name":             "wea_relhum",
    "shortDesc":        "WEA_RELHUM",
    "type":             "float",
    "decimalPlaces":        2,
    "default":              null
},
{
    "name":             "wea_dewpt",
    "shortDesc":        "WEA_DEWPT",
    "type":             "float",
    "decimalPlaces":        2,
    "default":              null
},
{
    "name":             "wea_windirt",
    "shortDesc":        "WEA_WINDIRT",
    "type":             "float",
    "decimalPlaces":        2,
    "default":              null
},
{
    "name":             "wea_winspdt",
    "shortDesc":        "WEA_WINSPDT",
    "type":             "float",
    "decimalPlaces":        2,
    "default":              null
},
{
    "name":             "wea_windirr",
    "shortDesc":        "WEA_WATRDIRR",
    "type":             "float",
    "decimalPlaces":        2,
    "default":              null
},
{
    "name":             "wea_watspdr",
    "shortDesc":        "WEA_WATSPDR",
    "type":             "float",
    "decimalPlaces":        2,
    "default":              null
},
{
    "name":             "wea_watdir",
    "shortDesc":        "WEA_WATDIR",
    "type":             "float",
    "decimalPlaces":        2,
    "default":              null
},
{
    "name":             "wea_watspd",
    "shortDesc":        "WEA_WATSPD",
    "type":             "float",
    "decimalPlaces":        2,
    "default":              null
},
{
    "name":             "wea_visibiran",
    "shortDesc":        "WEA_VISIBIRAN",
    "type":             "float",
    "decimalPlaces":        2,
    "default":              null
},
{
    "name":             "nav_mode",
    "shortDesc":        "NAV_MODE",
    "type":             "float",
    "decimalPlaces":    2,
    "default":              null
}
]
}
